lmformatenforcer/__init__.py
lmformatenforcer/analyzer.py
lmformatenforcer/characterlevelparser.py
lmformatenforcer/consts.py
lmformatenforcer/exceptions.py
lmformatenforcer/external/__init__.py
lmformatenforcer/external/jsonschemaobject.py
lmformatenforcer/external/jsonschemaobjectutil.py
lmformatenforcer/integrations/__init__.py
lmformatenforcer/integrations/exllamav2.py
lmformatenforcer/integrations/haystackv1.py
lmformatenforcer/integrations/haystackv2.py
lmformatenforcer/integrations/llamacpp.py
lmformatenforcer/integrations/transformers.py
lmformatenforcer/integrations/trtllm.py
lmformatenforcer/integrations/vllm.py
lmformatenforcer/jsonschemaparser.py
lmformatenforcer/regexparser.py
lmformatenforcer/tokenenforcer.py
lmformatenforcer/tokenizerprefixtree.py
lmformatenforcer/tokenlist.py
lm_format_enforcer-0.11.2.dist-info/LICENSE
lm_format_enforcer-0.11.2.dist-info/METADATA
lm_format_enforcer-0.11.2.dist-info/WHEEL
lm_format_enforcer-0.11.2.dist-info/RECORD
