Metadata-Version: 2.3
Name: lm-format-enforcer
Version: 0.11.2
Summary: Enforce the output format (JSON Schema, Regex etc) of a language model
License: MIT
Author: Noam Gat
Author-email: noamgat@gmail.com
Requires-Python: >=3.8,<4.0
Classifier: Development Status :: 3 - Alpha
Classifier: Intended Audience :: Developers
Classifier: License :: OSI Approved :: MIT License
Classifier: Operating System :: OS Independent
Classifier: Programming Language :: Python
Classifier: Programming Language :: Python :: 3
Classifier: Programming Language :: Python :: 3.8
Classifier: Programming Language :: Python :: 3.9
Classifier: Programming Language :: Python :: 3.10
Classifier: Programming Language :: Python :: 3.11
Classifier: Programming Language :: Python :: 3.12
Classifier: Programming Language :: Python :: 3.13
Classifier: Programming Language :: Python :: 3 :: Only
Classifier: Topic :: Software Development :: Libraries :: Python Modules
Requires-Dist: interegular (>=0.3.2)
Requires-Dist: packaging
Requires-Dist: pydantic (>=1.10.8)
Requires-Dist: pyyaml
Project-URL: Bug Tracker, https://github.com/noamgat/lm-format-enforcer/issues
Project-URL: Documentation, https://github.com/noamgat/lm-format-enforcer
Project-URL: Homepage, https://github.com/noamgat/lm-format-enforcer
Project-URL: Repository, https://github.com/noamgat/lm-format-enforcer
